{
    "#floods": [
        {
            "id": "1054507018810089472",
            "like": "3",
            "replies": "0",
            "retweets": "1",
            "text": "Climatechange is REAL...unusual weather events in Queensland 2018\nhttps://www.news.com.au/technology/environment/huge-storms-lash-queensland-and-a-new-rain-event-could-be-on-the-way/news-story/f060ead045c4c7633deb6ae007190dda\u00a0\u2026\n#environment #auspol #climatechange #GlobalWarming #heatwave #floods #storms",
            "timestamp": "2018-10-22 22:57:19",
            "user": "EnviroBlog_AU"
        },
        {
            "id": "1054503516687884289",
            "like": "0",
            "replies": "0",
            "retweets": "1",
            "text": "Columbia Engineers find rising temperatures and human activity are increasing storm runoff and flash #floods https://eurekalert.org/e/8rxp\u00a0 via @CUSEAS @EurekAlert",
            "timestamp": "2018-10-22 22:43:24",
            "user": "DocsEnvAus"
        },
        {
            "id": "1054473521458483200",
            "like": "0",
            "replies": "0",
            "retweets": "0",
            "text": "The Guardian:Politicians say nothing, but #US #farmers are increasingly terrified by it \u2013 climate change\n#ClimateChange #Haiku\nMore #droughts and #floods from\nClimate change hurt #food crop yields.\nAdapt now or fail.\n#CropYield\u2026 https://natureorderzociety.wordpress.com/2018/10/22/the-guardian-politicians-say-nothing-but-us-farmers-are-increasingly-terrified-by-it-climate-change/\u00a0\u2026pic.twitter.com/0TxmoWluHw",
            "timestamp": "2018-10-22 20:44:13",
            "user": "NatorzOrg"
        },
        {
            "id": "1054464836359331840",
            "like": "2",
            "replies": "0",
            "retweets": "0",
            "text": "Rising temperatures and human activity are increasing storm #runoff and flash #floods http://bit.ly/2q8hT2Z\u00a0pic.twitter.com/ZU8qX899XF",
            "timestamp": "2018-10-22 20:09:42",
            "user": "CUSEAS"
        },
        {
            "id": "1054450947865362433",
            "like": "2",
            "replies": "0",
            "retweets": "1",
            "text": "The approved design of Windermere Road carpark includes a flood basin intended to hold storm water. The design stipulates \u2018to be cleared of all vegetation\u2019. This is a picture of the \u201cflood basin\u201d today. #overgrown #floods #grangeoversandspic.twitter.com/VZ8CrdLwqJ",
            "timestamp": "2018-10-22 19:14:31",
            "user": "GrangeUnder"
        },
        {
            "id": "1054441580193570816",
            "like": "0",
            "replies": "0",
            "retweets": "0",
            "text": " El Clima extremo no para en Oriente medio , en este instante una severa tormemta golpea #Bahr\u00e9in  isla del Golfo P\u00e9rsico #video #floods #rain #flooding #storm 22/10\nhttps://m.facebook.com/story.php?story_fbid=10217290924043549&id=1185863371\u00a0\u2026",
            "timestamp": "2018-10-22 18:37:17",
            "user": "Giulian30936403"
        },
        {
            "id": "1054428439489536000",
            "like": "1",
            "replies": "0",
            "retweets": "0",
            "text": "Our GES DISC archive & Giovanni system have both #precipitation data from satellites & assimilation models, & hydrological variables (incl. soil moisture & runoff) suitable for examining events & trends related to this topic. #floods #hydrology @NASARain @NASA_LIS @NASAEarthDatahttps://twitter.com/EurekAlert/status/1054426517948850176\u00a0\u2026",
            "timestamp": "2018-10-22 17:45:04",
            "user": "NASA_GESDISC"
        },
        {
            "id": "1054422973065687044",
            "like": "0",
            "replies": "0",
            "retweets": "0",
            "text": "Young people, U.S. Supreme Court, and a climate change case. #climate #publicpolicy #democracy #hurricanes #fires #floods #drought #extremetemps #FoodSecurityhttps://twitter.com/youthvgov/status/1054406410186846210\u00a0\u2026",
            "timestamp": "2018-10-22 17:23:21",
            "user": "ungaro"
        },
        {
            "id": "1054419612434087941",
            "like": "0",
            "replies": "1",
            "retweets": "0",
            "text": "Flood-hit residents claim all pleas for help were ignored\n\n#bahrainnews #bahrain #floods #torrentialrains #residents #claimforhelp \n\n Read more: \nhttp://www.gdnonline.com/Details/426948/Flood-hit-residents-claim-all-pleas-for-help-were-ignored\u00a0\u2026pic.twitter.com/uThK7ZoPer",
            "timestamp": "2018-10-22 17:10:00",
            "user": "GDNonline"
        },
        {
            "id": "1054414578975735808",
            "like": "1",
            "replies": "0",
            "retweets": "0",
            "text": "'Flooding caused by torrential rains have turned homes into swimming pools'\n\n#bahrainnews #bahrain #floods #flooding #torrentialrains \n\n Read more: \nhttp://www.gdnonline.com/Details/426947/Flooding-caused-by-torrential-rains-have-turned-homes-into-swimming-pools\u00a0\u2026pic.twitter.com/Xz9pMyUpOV",
            "timestamp": "2018-10-22 16:50:00",
            "user": "GDNonline"
        }
    ]
}